[
  {
    "event_type": "inventory_movements",
    "event_id": "b7e901e2-2f0f-4b41-92c9-997ded0202c6",
    "movement_id": "MOV-1960",
    "movement_type": "unpick",
    "movement_date": "2026-03-31",
    "warehouse_id": "W01",
    "destination_warehouse_id": null,
    "sku": "FF-BF100-S316-PN63-FM",
    "quantity": 107,
    "quantity_direction": "in",
    "order_id": "ORD-2026-001463",
    "order_line_id": "ORD-2026-001463-L1",
    "production_batch_id": null,
    "reason_code": null,
    "reference_id": null
  },
  {
    "event_type": "inventory_movements",
    "event_id": "8b681332-c351-468a-aae7-6fd60d97ee2f",
    "movement_id": "MOV-1961",
    "movement_type": "receipt",
    "movement_date": "2026-03-31",
    "warehouse_id": "W01",
    "destination_warehouse_id": null,
    "sku": "FF-GT150-S316-PN40-TM",
    "quantity": 244,
    "quantity_direction": "in",
    "order_id": null,
    "order_line_id": null,
    "production_batch_id": "BATCH-1324",
    "reason_code": null,
    "reference_id": "GRADE-A"
  },
  {
    "event_type": "inventory_movements",
    "event_id": "fe89fb59-05ab-4b73-ac90-cb4d8aa82a17",
    "movement_id": "MOV-1962",
    "movement_type": "receipt",
    "movement_date": "2026-03-31",
    "warehouse_id": "W01",
    "destination_warehouse_id": null,
    "sku": "FF-CK40-S316-PN10-FP",
    "quantity": 239,
    "quantity_direction": "in",
    "order_id": null,
    "order_line_id": null,
    "production_batch_id": "BATCH-1325",
    "reason_code": null,
    "reference_id": "GRADE-A"
  },
  {
    "event_type": "inventory_movements",
    "event_id": "8c206ea2-188a-46f5-834d-7923a580ba8c",
    "movement_id": "MOV-1963",
    "movement_type": "transfer",
    "movement_date": "2026-03-31",
    "warehouse_id": "W02",
    "destination_warehouse_id": "W01",
    "sku": "FF-GT100-CS-PN40-WP",
    "quantity": 1,
    "quantity_direction": "out",
    "order_id": null,
    "order_line_id": null,
    "production_batch_id": null,
    "reason_code": "adhoc_transfer",
    "reference_id": null
  },
  {
    "event_type": "inventory_movements",
    "event_id": "07f32190-d4cf-4040-91fd-9d773484d89e",
    "movement_id": "MOV-1964",
    "movement_type": "transfer",
    "movement_date": "2026-03-31",
    "warehouse_id": "W01",
    "destination_warehouse_id": null,
    "sku": "FF-GT100-CS-PN40-WP",
    "quantity": 1,
    "quantity_direction": "in",
    "order_id": null,
    "order_line_id": null,
    "production_batch_id": null,
    "reason_code": "adhoc_transfer",
    "reference_id": "W02"
  },
  {
    "event_type": "inventory_movements",
    "event_id": "eb845404-be10-49a6-b6e8-b9d3a82a1fc3",
    "movement_id": "MOV-1965",
    "movement_type": "transfer",
    "movement_date": "2026-03-31",
    "warehouse_id": "W01",
    "destination_warehouse_id": "W02",
    "sku": "FF-GT80-CS-PN40-TM",
    "quantity": 31,
    "quantity_direction": "out",
    "order_id": null,
    "order_line_id": null,
    "production_batch_id": null,
    "reason_code": "replenishment",
    "reference_id": null
  },
  {
    "event_type": "inventory_movements",
    "event_id": "29f4d4f5-2252-4b31-9926-cdefb8794001",
    "movement_id": "MOV-1966",
    "movement_type": "transfer",
    "movement_date": "2026-03-31",
    "warehouse_id": "W02",
    "destination_warehouse_id": null,
    "sku": "FF-GT80-CS-PN40-TM",
    "quantity": 31,
    "quantity_direction": "in",
    "order_id": null,
    "order_line_id": null,
    "production_batch_id": null,
    "reason_code": "replenishment",
    "reference_id": "W01"
  },
  {
    "event_type": "inventory_movements",
    "event_id": "c1090474-aa6f-4e10-b906-1fa133be594d",
    "movement_id": "MOV-1967",
    "movement_type": "transfer",
    "movement_date": "2026-03-31",
    "warehouse_id": "W01",
    "destination_warehouse_id": "W02",
    "sku": "FF-BF100-S316-PN16-WE",
    "quantity": 27,
    "quantity_direction": "out",
    "order_id": null,
    "order_line_id": null,
    "production_batch_id": null,
    "reason_code": "replenishment",
    "reference_id": null
  },
  {
    "event_type": "inventory_movements",
    "event_id": "56ef9471-2e3e-41e2-9c96-bdaee2a44d43",
    "movement_id": "MOV-1968",
    "movement_type": "transfer",
    "movement_date": "2026-03-31",
    "warehouse_id": "W02",
    "destination_warehouse_id": null,
    "sku": "FF-BF100-S316-PN16-WE",
    "quantity": 27,
    "quantity_direction": "in",
    "order_id": null,
    "order_line_id": null,
    "production_batch_id": null,
    "reason_code": "replenishment",
    "reference_id": "W01"
  },
  {
    "event_type": "inventory_movements",
    "event_id": "04c4dfe2-5099-4a61-af46-22dc22bd0d1e",
    "movement_id": "MOV-1969",
    "movement_type": "transfer",
    "movement_date": "2026-03-31",
    "warehouse_id": "W01",
    "destination_warehouse_id": "W02",
    "sku": "FF-ND25-S316-PN16-FM",
    "quantity": 21,
    "quantity_direction": "out",
    "order_id": null,
    "order_line_id": null,
    "production_batch_id": null,
    "reason_code": "replenishment",
    "reference_id": null
  },
  {
    "event_type": "inventory_movements",
    "event_id": "37f51bba-cf7c-49b2-8f32-de6a3cc7e37a",
    "movement_id": "MOV-1970",
    "movement_type": "transfer",
    "movement_date": "2026-03-31",
    "warehouse_id": "W02",
    "destination_warehouse_id": null,
    "sku": "FF-ND25-S316-PN16-FM",
    "quantity": 21,
    "quantity_direction": "in",
    "order_id": null,
    "order_line_id": null,
    "production_batch_id": null,
    "reason_code": "replenishment",
    "reference_id": "W01"
  },
  {
    "event_type": "inventory_movements",
    "event_id": "74c8b07a-1499-499b-a8a7-60aca37bef70",
    "movement_id": "MOV-1971",
    "movement_type": "transfer",
    "movement_date": "2026-03-31",
    "warehouse_id": "W01",
    "destination_warehouse_id": "W02",
    "sku": "FF-BL200-DPX-PN16-WH",
    "quantity": 9,
    "quantity_direction": "out",
    "order_id": null,
    "order_line_id": null,
    "production_batch_id": null,
    "reason_code": "replenishment",
    "reference_id": null
  },
  {
    "event_type": "inventory_movements",
    "event_id": "01cad74c-1bf5-44ae-8b12-448065e67182",
    "movement_id": "MOV-1972",
    "movement_type": "transfer",
    "movement_date": "2026-03-31",
    "warehouse_id": "W02",
    "destination_warehouse_id": null,
    "sku": "FF-BL200-DPX-PN16-WH",
    "quantity": 9,
    "quantity_direction": "in",
    "order_id": null,
    "order_line_id": null,
    "production_batch_id": null,
    "reason_code": "replenishment",
    "reference_id": "W01"
  },
  {
    "event_type": "inventory_movements",
    "event_id": "c0d6b478-dd27-4fe4-a35c-2a8465f032a1",
    "movement_id": "MOV-1973",
    "movement_type": "transfer",
    "movement_date": "2026-03-31",
    "warehouse_id": "W01",
    "destination_warehouse_id": "W02",
    "sku": "FF-BL80-DPX-PN10-WP",
    "quantity": 14,
    "quantity_direction": "out",
    "order_id": null,
    "order_line_id": null,
    "production_batch_id": null,
    "reason_code": "replenishment",
    "reference_id": null
  },
  {
    "event_type": "inventory_movements",
    "event_id": "d76d5bee-3a7f-4c9d-81ec-911fc1434e85",
    "movement_id": "MOV-1974",
    "movement_type": "transfer",
    "movement_date": "2026-03-31",
    "warehouse_id": "W02",
    "destination_warehouse_id": null,
    "sku": "FF-BL80-DPX-PN10-WP",
    "quantity": 14,
    "quantity_direction": "in",
    "order_id": null,
    "order_line_id": null,
    "production_batch_id": null,
    "reason_code": "replenishment",
    "reference_id": "W01"
  }
]