[
  {
    "event_type": "credit_hold",
    "event_id": "477dcb11-04ca-4d11-9d04-172b6a69d0d4",
    "simulation_date": "2026-06-11",
    "order_id": "ORD-2026-001253",
    "customer_id": "CUST-0022",
    "customer_balance_pln": 81253.89,
    "open_orders_value_pln": 9225537.11,
    "credit_limit_pln": 164198.41,
    "exposure_pln": 9306791.0
  },
  {
    "event_type": "credit_hold",
    "event_id": "a1b8ca8c-64d7-490d-bdf0-f1329e28ff17",
    "simulation_date": "2026-06-11",
    "order_id": "ORD-2026-001296",
    "customer_id": "CUST-0022",
    "customer_balance_pln": 81253.89,
    "open_orders_value_pln": 9200092.25,
    "credit_limit_pln": 164198.41,
    "exposure_pln": 9281346.14
  },
  {
    "event_type": "credit_hold",
    "event_id": "1f23bdb8-7920-4869-9391-5b4df2c78776",
    "simulation_date": "2026-06-11",
    "order_id": "ORD-2026-001309",
    "customer_id": "CUST-0022",
    "customer_balance_pln": 81253.89,
    "open_orders_value_pln": 9002028.23,
    "credit_limit_pln": 164198.41,
    "exposure_pln": 9083282.12
  },
  {
    "event_type": "credit_hold",
    "event_id": "4d5a6a14-b523-4568-80fc-e6e9be5ca816",
    "simulation_date": "2026-06-11",
    "order_id": "ORD-2026-001344",
    "customer_id": "CUST-0022",
    "customer_balance_pln": 81253.89,
    "open_orders_value_pln": 8981920.23,
    "credit_limit_pln": 164198.41,
    "exposure_pln": 9063174.12
  },
  {
    "event_type": "credit_hold",
    "event_id": "15d6a317-3a1f-459c-9216-edefe8fb330b",
    "simulation_date": "2026-06-11",
    "order_id": "ORD-2026-001378",
    "customer_id": "CUST-0022",
    "customer_balance_pln": 81253.89,
    "open_orders_value_pln": 8945766.06,
    "credit_limit_pln": 164198.41,
    "exposure_pln": 9027019.95
  },
  {
    "event_type": "credit_hold",
    "event_id": "646f2f3c-7546-4950-a570-5e56f8ef3ae5",
    "simulation_date": "2026-06-11",
    "order_id": "ORD-2026-001412",
    "customer_id": "CUST-0022",
    "customer_balance_pln": 81253.89,
    "open_orders_value_pln": 8664556.27,
    "credit_limit_pln": 164198.41,
    "exposure_pln": 8745810.16
  },
  {
    "event_type": "credit_hold",
    "event_id": "d55ed936-ac74-4678-bf1b-23460786d971",
    "simulation_date": "2026-06-11",
    "order_id": "ORD-2026-001424",
    "customer_id": "CUST-0022",
    "customer_balance_pln": 81253.89,
    "open_orders_value_pln": 8599358.62,
    "credit_limit_pln": 164198.41,
    "exposure_pln": 8680612.51
  },
  {
    "event_type": "credit_hold",
    "event_id": "c2236d08-470a-4ff4-aa0a-b4e515bad1b2",
    "simulation_date": "2026-06-11",
    "order_id": "ORD-2026-001437",
    "customer_id": "CUST-0022",
    "customer_balance_pln": 81253.89,
    "open_orders_value_pln": 8319299.61,
    "credit_limit_pln": 164198.41,
    "exposure_pln": 8400553.5
  },
  {
    "event_type": "credit_hold",
    "event_id": "989c2eb4-b10f-4fc6-bf9a-d2654382140e",
    "simulation_date": "2026-06-11",
    "order_id": "ORD-2026-001509",
    "customer_id": "CUST-0022",
    "customer_balance_pln": 81253.89,
    "open_orders_value_pln": 8256096.71,
    "credit_limit_pln": 164198.41,
    "exposure_pln": 8337350.6
  },
  {
    "event_type": "credit_hold",
    "event_id": "41eb04e9-9dbe-4399-b2f9-380fb36af679",
    "simulation_date": "2026-06-11",
    "order_id": "ORD-2026-001517",
    "customer_id": "CUST-0022",
    "customer_balance_pln": 81253.89,
    "open_orders_value_pln": 7939670.58,
    "credit_limit_pln": 164198.41,
    "exposure_pln": 8020924.47
  },
  {
    "event_type": "credit_hold",
    "event_id": "b54f97d0-df75-40da-973e-cff85a21db3a",
    "simulation_date": "2026-06-11",
    "order_id": "ORD-2026-001535",
    "customer_id": "CUST-0022",
    "customer_balance_pln": 81253.89,
    "open_orders_value_pln": 7427540.64,
    "credit_limit_pln": 164198.41,
    "exposure_pln": 7508794.53
  },
  {
    "event_type": "credit_hold",
    "event_id": "5f378661-70fe-430c-be3e-c5393be1079e",
    "simulation_date": "2026-06-11",
    "order_id": "ORD-2026-001537",
    "customer_id": "CUST-0022",
    "customer_balance_pln": 81253.89,
    "open_orders_value_pln": 5928820.12,
    "credit_limit_pln": 164198.41,
    "exposure_pln": 6010074.01
  },
  {
    "event_type": "credit_hold",
    "event_id": "d73f3e1e-f614-4499-a63d-48a412aa385c",
    "simulation_date": "2026-06-11",
    "order_id": "ORD-2026-001553",
    "customer_id": "CUST-0022",
    "customer_balance_pln": 81253.89,
    "open_orders_value_pln": 5775068.28,
    "credit_limit_pln": 164198.41,
    "exposure_pln": 5856322.17
  },
  {
    "event_type": "credit_hold",
    "event_id": "5ceebf46-841d-48fe-87f0-f69bf2c9258f",
    "simulation_date": "2026-06-11",
    "order_id": "ORD-2026-001582",
    "customer_id": "CUST-0022",
    "customer_balance_pln": 81253.89,
    "open_orders_value_pln": 5611045.25,
    "credit_limit_pln": 164198.41,
    "exposure_pln": 5692299.14
  },
  {
    "event_type": "credit_hold",
    "event_id": "85b92d23-f2a4-4a93-a96b-0e8d38e302ff",
    "simulation_date": "2026-06-11",
    "order_id": "ORD-2026-001594",
    "customer_id": "CUST-0022",
    "customer_balance_pln": 81253.89,
    "open_orders_value_pln": 5560123.49,
    "credit_limit_pln": 164198.41,
    "exposure_pln": 5641377.38
  },
  {
    "event_type": "credit_hold",
    "event_id": "9a28c63f-e6ea-451a-8966-6f116638abd9",
    "simulation_date": "2026-06-11",
    "order_id": "ORD-2026-001605",
    "customer_id": "CUST-0022",
    "customer_balance_pln": 81253.89,
    "open_orders_value_pln": 5529527.21,
    "credit_limit_pln": 164198.41,
    "exposure_pln": 5610781.1
  },
  {
    "event_type": "credit_hold",
    "event_id": "7ea5a7fe-f5e3-4212-b549-110b21eda13e",
    "simulation_date": "2026-06-11",
    "order_id": "ORD-2026-001645",
    "customer_id": "CUST-0022",
    "customer_balance_pln": 81253.89,
    "open_orders_value_pln": 5412084.73,
    "credit_limit_pln": 164198.41,
    "exposure_pln": 5493338.62
  },
  {
    "event_type": "credit_hold",
    "event_id": "d5e66f80-46c9-41cc-a022-91029cb96de0",
    "simulation_date": "2026-06-11",
    "order_id": "ORD-2026-001661",
    "customer_id": "CUST-0022",
    "customer_balance_pln": 81253.89,
    "open_orders_value_pln": 5355369.63,
    "credit_limit_pln": 164198.41,
    "exposure_pln": 5436623.52
  },
  {
    "event_type": "credit_hold",
    "event_id": "77404025-faa9-4eaa-9566-9e22dd188684",
    "simulation_date": "2026-06-11",
    "order_id": "ORD-2026-001689",
    "customer_id": "CUST-0022",
    "customer_balance_pln": 81253.89,
    "open_orders_value_pln": 5310464.35,
    "credit_limit_pln": 164198.41,
    "exposure_pln": 5391718.24
  },
  {
    "event_type": "credit_hold",
    "event_id": "9da9f859-6841-4df4-9db3-11055e50b661",
    "simulation_date": "2026-06-11",
    "order_id": "ORD-2026-001702",
    "customer_id": "CUST-0022",
    "customer_balance_pln": 81253.89,
    "open_orders_value_pln": 5114144.27,
    "credit_limit_pln": 164198.41,
    "exposure_pln": 5195398.16
  },
  {
    "event_type": "credit_hold",
    "event_id": "51decb4a-19ad-4c12-b42c-a99f27204065",
    "simulation_date": "2026-06-11",
    "order_id": "ORD-2026-001711",
    "customer_id": "CUST-0022",
    "customer_balance_pln": 81253.89,
    "open_orders_value_pln": 5056064.05,
    "credit_limit_pln": 164198.41,
    "exposure_pln": 5137317.94
  },
  {
    "event_type": "credit_hold",
    "event_id": "e86bbf13-48a4-4a5e-a3a2-4400cab8efdd",
    "simulation_date": "2026-06-11",
    "order_id": "ORD-2026-001750",
    "customer_id": "CUST-0022",
    "customer_balance_pln": 81253.89,
    "open_orders_value_pln": 2601846.05,
    "credit_limit_pln": 164198.41,
    "exposure_pln": 2683099.94
  },
  {
    "event_type": "credit_hold",
    "event_id": "288d05b2-cd29-4064-bbaa-b779f20ee2ce",
    "simulation_date": "2026-06-11",
    "order_id": "ORD-2026-001772",
    "customer_id": "CUST-0022",
    "customer_balance_pln": 81253.89,
    "open_orders_value_pln": 2570842.98,
    "credit_limit_pln": 164198.41,
    "exposure_pln": 2652096.87
  },
  {
    "event_type": "credit_hold",
    "event_id": "08f5cf29-8d38-433c-a6c8-98855741e4ae",
    "simulation_date": "2026-06-11",
    "order_id": "ORD-2026-001890",
    "customer_id": "CUST-0022",
    "customer_balance_pln": 81253.89,
    "open_orders_value_pln": 2466679.88,
    "credit_limit_pln": 164198.41,
    "exposure_pln": 2547933.77
  },
  {
    "event_type": "credit_hold",
    "event_id": "b0a291bf-2a97-4bf9-9945-3e13e9d6b5c7",
    "simulation_date": "2026-06-11",
    "order_id": "ORD-2026-001908",
    "customer_id": "CUST-0022",
    "customer_balance_pln": 81253.89,
    "open_orders_value_pln": 2010697.31,
    "credit_limit_pln": 164198.41,
    "exposure_pln": 2091951.2
  },
  {
    "event_type": "credit_hold",
    "event_id": "68ce926e-6fba-4fe3-83b3-44ca7c5d7122",
    "simulation_date": "2026-06-11",
    "order_id": "ORD-2026-001915",
    "customer_id": "CUST-0022",
    "customer_balance_pln": 81253.89,
    "open_orders_value_pln": 1550995.33,
    "credit_limit_pln": 164198.41,
    "exposure_pln": 1632249.22
  },
  {
    "event_type": "credit_hold",
    "event_id": "08d825f7-6396-4a8e-b8f2-c9d5c4683209",
    "simulation_date": "2026-06-11",
    "order_id": "ORD-2026-001926",
    "customer_id": "CUST-0022",
    "customer_balance_pln": 81253.89,
    "open_orders_value_pln": 238143.74,
    "credit_limit_pln": 164198.41,
    "exposure_pln": 319397.63
  },
  {
    "event_type": "credit_hold",
    "event_id": "06897ef6-e08c-4f22-a205-5ff5312056b7",
    "simulation_date": "2026-06-11",
    "order_id": "ORD-2026-001985",
    "customer_id": "CUST-0022",
    "customer_balance_pln": 81253.89,
    "open_orders_value_pln": 195358.36,
    "credit_limit_pln": 164198.41,
    "exposure_pln": 276612.25
  },
  {
    "event_type": "credit_hold",
    "event_id": "e83f57e6-ee18-45e8-b5c2-b0d3fef2679f",
    "simulation_date": "2026-06-11",
    "order_id": "ORD-2026-002009",
    "customer_id": "CUST-0002",
    "customer_balance_pln": 0.0,
    "open_orders_value_pln": 1011926.94,
    "credit_limit_pln": 130247.78,
    "exposure_pln": 1011926.94
  },
  {
    "event_type": "credit_hold",
    "event_id": "8ca8061c-138a-4804-aa9a-9b8fa9f83052",
    "simulation_date": "2026-06-11",
    "order_id": "ORD-2026-002010",
    "customer_id": "CUST-0013",
    "customer_balance_pln": 81207.06,
    "open_orders_value_pln": 215255.29,
    "credit_limit_pln": 117418.39,
    "exposure_pln": 296462.35
  },
  {
    "event_type": "credit_hold",
    "event_id": "8b33683a-cb60-412b-9fce-9bbff5545c98",
    "simulation_date": "2026-06-11",
    "order_id": "ORD-2026-002011",
    "customer_id": "CUST-0017",
    "customer_balance_pln": 18702.18,
    "open_orders_value_pln": 260918.83,
    "credit_limit_pln": 198457.0,
    "exposure_pln": 279621.01
  },
  {
    "event_type": "credit_hold",
    "event_id": "d6e45a66-1cb3-4df5-911a-ac72958691d7",
    "simulation_date": "2026-06-11",
    "order_id": "ORD-2026-002012",
    "customer_id": "CUST-0027",
    "customer_balance_pln": 94069.71,
    "open_orders_value_pln": 23974.88,
    "credit_limit_pln": 22627.24,
    "exposure_pln": 118044.59
  },
  {
    "event_type": "credit_hold",
    "event_id": "290c47c9-291f-476a-a59a-ddaf8fc43570",
    "simulation_date": "2026-06-11",
    "order_id": "ORD-2026-002013",
    "customer_id": "CUST-0045",
    "customer_balance_pln": 0.0,
    "open_orders_value_pln": 8635000.4,
    "credit_limit_pln": 1451560.77,
    "exposure_pln": 8635000.4
  },
  {
    "event_type": "credit_hold",
    "event_id": "3a30c625-d5cc-4487-a810-d27ea4f747c5",
    "simulation_date": "2026-06-11",
    "order_id": "ORD-2026-002014",
    "customer_id": "CUST-0057",
    "customer_balance_pln": 0.0,
    "open_orders_value_pln": 4961972.17,
    "credit_limit_pln": 897772.02,
    "exposure_pln": 4961972.17
  },
  {
    "event_type": "credit_release",
    "event_id": "8b851933-5220-452a-9950-7e596077fbeb",
    "simulation_date": "2026-06-11",
    "order_id": "ORD-2026-001193",
    "customer_id": "CUST-0016",
    "customer_balance_pln": 0.0,
    "open_orders_value_pln": 0.0,
    "credit_limit_pln": 1811975.3,
    "exposure_pln": 0.0
  },
  {
    "event_type": "credit_release",
    "event_id": "3770eaae-3c61-4105-b319-8b53b6edae1f",
    "simulation_date": "2026-06-11",
    "order_id": "ORD-2026-001229",
    "customer_id": "CUST-0016",
    "customer_balance_pln": 0.0,
    "open_orders_value_pln": 0.0,
    "credit_limit_pln": 1811975.3,
    "exposure_pln": 0.0
  },
  {
    "event_type": "credit_release",
    "event_id": "5464b828-670b-4565-ad4e-844a1b056739",
    "simulation_date": "2026-06-11",
    "order_id": "ORD-2026-001265",
    "customer_id": "CUST-0016",
    "customer_balance_pln": 0.0,
    "open_orders_value_pln": 0.0,
    "credit_limit_pln": 1811975.3,
    "exposure_pln": 0.0
  },
  {
    "event_type": "credit_release",
    "event_id": "38b9a71e-e7b8-488f-b46c-9d2f187a2806",
    "simulation_date": "2026-06-11",
    "order_id": "ORD-2026-001288",
    "customer_id": "CUST-0016",
    "customer_balance_pln": 0.0,
    "open_orders_value_pln": 0.0,
    "credit_limit_pln": 1811975.3,
    "exposure_pln": 0.0
  },
  {
    "event_type": "credit_release",
    "event_id": "851f91cb-7ba3-4a1e-89c6-bf749a9c8b49",
    "simulation_date": "2026-06-11",
    "order_id": "ORD-2026-001365",
    "customer_id": "CUST-0016",
    "customer_balance_pln": 0.0,
    "open_orders_value_pln": 0.0,
    "credit_limit_pln": 1811975.3,
    "exposure_pln": 0.0
  },
  {
    "event_type": "credit_release",
    "event_id": "4afed3c5-ea06-4013-a33a-49c7cc5cf1e1",
    "simulation_date": "2026-06-11",
    "order_id": "ORD-2026-001395",
    "customer_id": "CUST-0016",
    "customer_balance_pln": 0.0,
    "open_orders_value_pln": 0.0,
    "credit_limit_pln": 1811975.3,
    "exposure_pln": 0.0
  },
  {
    "event_type": "credit_release",
    "event_id": "e5af9f93-3a11-4ead-8638-4c75ba5c9a87",
    "simulation_date": "2026-06-11",
    "order_id": "ORD-2026-001409",
    "customer_id": "CUST-0016",
    "customer_balance_pln": 0.0,
    "open_orders_value_pln": 0.0,
    "credit_limit_pln": 1811975.3,
    "exposure_pln": 0.0
  },
  {
    "event_type": "credit_release",
    "event_id": "9ab4232f-8041-4574-8074-4cf4fae8616d",
    "simulation_date": "2026-06-11",
    "order_id": "ORD-2026-001422",
    "customer_id": "CUST-0016",
    "customer_balance_pln": 0.0,
    "open_orders_value_pln": 0.0,
    "credit_limit_pln": 1811975.3,
    "exposure_pln": 0.0
  },
  {
    "event_type": "credit_release",
    "event_id": "6735ca38-6951-4b39-a52f-26e397e6e1b9",
    "simulation_date": "2026-06-11",
    "order_id": "ORD-2026-001434",
    "customer_id": "CUST-0016",
    "customer_balance_pln": 0.0,
    "open_orders_value_pln": 0.0,
    "credit_limit_pln": 1811975.3,
    "exposure_pln": 0.0
  },
  {
    "event_type": "credit_release",
    "event_id": "4b7edaf0-2868-4905-8a55-9e1bb29889fe",
    "simulation_date": "2026-06-11",
    "order_id": "ORD-2026-001778",
    "customer_id": "CUST-0016",
    "customer_balance_pln": 0.0,
    "open_orders_value_pln": 0.0,
    "credit_limit_pln": 1811975.3,
    "exposure_pln": 0.0
  },
  {
    "event_type": "credit_release",
    "event_id": "15f27806-b376-47b2-9474-3f7b5d9ad5c8",
    "simulation_date": "2026-06-11",
    "order_id": "ORD-2026-001786",
    "customer_id": "CUST-0016",
    "customer_balance_pln": 0.0,
    "open_orders_value_pln": 0.0,
    "credit_limit_pln": 1811975.3,
    "exposure_pln": 0.0
  },
  {
    "event_type": "credit_release",
    "event_id": "33896514-aa85-485c-8e4a-a573e87c1c65",
    "simulation_date": "2026-06-11",
    "order_id": "ORD-2026-001796",
    "customer_id": "CUST-0016",
    "customer_balance_pln": 0.0,
    "open_orders_value_pln": 0.0,
    "credit_limit_pln": 1811975.3,
    "exposure_pln": 0.0
  },
  {
    "event_type": "credit_release",
    "event_id": "c39e8981-3967-4436-84d0-0eb930628369",
    "simulation_date": "2026-06-11",
    "order_id": "ORD-2026-001870",
    "customer_id": "CUST-0016",
    "customer_balance_pln": 0.0,
    "open_orders_value_pln": 0.0,
    "credit_limit_pln": 1811975.3,
    "exposure_pln": 0.0
  }
]