[
  {
    "event_type": "load_event",
    "event_id": "445f7c46-3fc3-4ae3-ade5-3f7f52f6b37e",
    "load_id": "LOAD-1047",
    "event_subtype": "delivered",
    "simulation_date": "2026-03-01",
    "sync_window": "14",
    "carrier_code": "RABEN",
    "source_warehouse_id": "W01",
    "shipment_ids": [
      "SHP-1059"
    ],
    "order_ids": [
      "ORD-2026-001227"
    ],
    "total_weight_kg": 9333.2,
    "weight_unit": "kg",
    "total_weight_reported": 9333.2,
    "status": "delivered",
    "planned_date": "2026-02-24",
    "priority": "critical",
    "customer_ids": [
      "CUST-0056"
    ],
    "destination_region": ""
  }
]