[
  {
    "event_type": "inventory_movements",
    "event_id": "29bbe802-d1d9-4a2e-8971-a89c5ddcb356",
    "movement_id": "MOV-4637",
    "movement_type": "receipt",
    "movement_date": "2026-11-20",
    "warehouse_id": "W01",
    "destination_warehouse_id": null,
    "sku": "FF-BL80-BRS-PN16-TP",
    "quantity": 142,
    "quantity_direction": "in",
    "order_id": null,
    "order_line_id": null,
    "production_batch_id": "BATCH-2226",
    "reason_code": null,
    "reference_id": "GRADE-A"
  },
  {
    "event_type": "inventory_movements",
    "event_id": "61c877cf-f9e1-48f2-b178-a6cbbc80108d",
    "movement_id": "MOV-4638",
    "movement_type": "receipt",
    "movement_date": "2026-11-20",
    "warehouse_id": "W01",
    "destination_warehouse_id": null,
    "sku": "FF-CK80-CS-PN63-TP",
    "quantity": 159,
    "quantity_direction": "in",
    "order_id": null,
    "order_line_id": null,
    "production_batch_id": "BATCH-2227",
    "reason_code": null,
    "reference_id": "GRADE-A"
  },
  {
    "event_type": "inventory_movements",
    "event_id": "d5f4c37f-bfad-4a12-92ca-c18b6b9793e3",
    "movement_id": "MOV-4639",
    "movement_type": "receipt",
    "movement_date": "2026-11-20",
    "warehouse_id": "W01",
    "destination_warehouse_id": null,
    "sku": "FF-GL50-CS-PN16-WM",
    "quantity": 172,
    "quantity_direction": "in",
    "order_id": null,
    "order_line_id": null,
    "production_batch_id": "BATCH-2228",
    "reason_code": null,
    "reference_id": "GRADE-A"
  },
  {
    "event_type": "inventory_movements",
    "event_id": "124b5b28-f102-4421-9967-003d37d0b744",
    "movement_id": "MOV-4640",
    "movement_type": "receipt",
    "movement_date": "2026-11-20",
    "warehouse_id": "W01",
    "destination_warehouse_id": null,
    "sku": "FF-GT50-S316-PN40-WM",
    "quantity": 145,
    "quantity_direction": "in",
    "order_id": null,
    "order_line_id": null,
    "production_batch_id": "BATCH-2229",
    "reason_code": null,
    "reference_id": "GRADE-A"
  },
  {
    "event_type": "inventory_movements",
    "event_id": "af0e84e7-0316-4201-b9d5-91371d3c802c",
    "movement_id": "MOV-4641",
    "movement_type": "scrap",
    "movement_date": "2026-11-20",
    "warehouse_id": "W01",
    "destination_warehouse_id": null,
    "sku": "FF-BL200-S316-PN10-TH",
    "quantity": 1,
    "quantity_direction": "out",
    "order_id": null,
    "order_line_id": null,
    "production_batch_id": null,
    "reason_code": "damaged_storage",
    "reference_id": null
  },
  {
    "event_type": "inventory_movements",
    "event_id": "82175ee1-448b-4ba5-a946-d4f8f15a3692",
    "movement_id": "MOV-4642",
    "movement_type": "scrap",
    "movement_date": "2026-11-20",
    "warehouse_id": "W01",
    "destination_warehouse_id": null,
    "sku": "FF-CK50-CS-PN16-TM",
    "quantity": 7,
    "quantity_direction": "out",
    "order_id": null,
    "order_line_id": null,
    "production_batch_id": null,
    "reason_code": "quality_reject",
    "reference_id": null
  },
  {
    "event_type": "inventory_movements",
    "event_id": "baed3eb9-c300-401a-b982-335e4ba11811",
    "movement_id": "MOV-4643",
    "movement_type": "scrap",
    "movement_date": "2026-11-20",
    "warehouse_id": "W01",
    "destination_warehouse_id": null,
    "sku": "FF-BF300-S304-PN16-TE",
    "quantity": 2,
    "quantity_direction": "out",
    "order_id": null,
    "order_line_id": null,
    "production_batch_id": null,
    "reason_code": "expired",
    "reference_id": null
  },
  {
    "event_type": "inventory_movements",
    "event_id": "3f0a3007-68bf-4d04-bf11-62a6ce0ef58f",
    "movement_id": "MOV-4644",
    "movement_type": "return_restock",
    "movement_date": "2026-11-20",
    "warehouse_id": "W01",
    "destination_warehouse_id": null,
    "sku": "FF-BF50-CS-PN16-XM",
    "quantity": 35,
    "quantity_direction": "in",
    "order_id": "ORD-2026-001807",
    "order_line_id": null,
    "production_batch_id": null,
    "reason_code": null,
    "reference_id": "GRADE-A"
  },
  {
    "event_type": "inventory_movements",
    "event_id": "891a10db-00df-470f-a8c9-e967cf58006d",
    "movement_id": "MOV-4645",
    "movement_type": "return_restock",
    "movement_date": "2026-11-20",
    "warehouse_id": "W01",
    "destination_warehouse_id": null,
    "sku": "FF-ND50-CS-PN25-FM",
    "quantity": 14,
    "quantity_direction": "in",
    "order_id": "ORD-2026-001807",
    "order_line_id": null,
    "production_batch_id": null,
    "reason_code": null,
    "reference_id": "GRADE-A"
  },
  {
    "event_type": "inventory_movements",
    "event_id": "a09b5e2e-a5e7-426c-b459-2dc2f271ddee",
    "movement_id": "MOV-4646",
    "movement_type": "return_restock",
    "movement_date": "2026-11-20",
    "warehouse_id": "W01",
    "destination_warehouse_id": null,
    "sku": "FF-BF25-S316-PN16-FE",
    "quantity": 26,
    "quantity_direction": "in",
    "order_id": "ORD-2026-001807",
    "order_line_id": null,
    "production_batch_id": null,
    "reason_code": null,
    "reference_id": "GRADE-A"
  },
  {
    "event_type": "inventory_movements",
    "event_id": "4efd44c5-7c37-4129-acd6-bf41cb812948",
    "movement_id": "MOV-4647",
    "movement_type": "transfer",
    "movement_date": "2026-11-20",
    "warehouse_id": "W01",
    "destination_warehouse_id": "W02",
    "sku": "FF-CK150-S304-PN16-FM",
    "quantity": 30,
    "quantity_direction": "out",
    "order_id": null,
    "order_line_id": null,
    "production_batch_id": null,
    "reason_code": "replenishment",
    "reference_id": null
  },
  {
    "event_type": "inventory_movements",
    "event_id": "8ed96e71-d145-4d28-b8ca-37e6b9fdc319",
    "movement_id": "MOV-4648",
    "movement_type": "transfer",
    "movement_date": "2026-11-20",
    "warehouse_id": "W02",
    "destination_warehouse_id": null,
    "sku": "FF-CK150-S304-PN16-FM",
    "quantity": 30,
    "quantity_direction": "in",
    "order_id": null,
    "order_line_id": null,
    "production_batch_id": null,
    "reason_code": "replenishment",
    "reference_id": "W01"
  },
  {
    "event_type": "inventory_movements",
    "event_id": "dc9b2a3a-3a7e-4d34-98b4-87a85eba2112",
    "movement_id": "MOV-4649",
    "movement_type": "transfer",
    "movement_date": "2026-11-20",
    "warehouse_id": "W01",
    "destination_warehouse_id": "W02",
    "sku": "FF-BL150-CS-PN40-TH",
    "quantity": 1,
    "quantity_direction": "out",
    "order_id": null,
    "order_line_id": null,
    "production_batch_id": null,
    "reason_code": "replenishment",
    "reference_id": null
  },
  {
    "event_type": "inventory_movements",
    "event_id": "96928f85-b954-410b-b0de-af23799c8824",
    "movement_id": "MOV-4650",
    "movement_type": "transfer",
    "movement_date": "2026-11-20",
    "warehouse_id": "W02",
    "destination_warehouse_id": null,
    "sku": "FF-BL150-CS-PN40-TH",
    "quantity": 1,
    "quantity_direction": "in",
    "order_id": null,
    "order_line_id": null,
    "production_batch_id": null,
    "reason_code": "replenishment",
    "reference_id": "W01"
  },
  {
    "event_type": "inventory_movements",
    "event_id": "145b2d01-264c-41bd-b9bf-dc718e91b8e7",
    "movement_id": "MOV-4651",
    "movement_type": "transfer",
    "movement_date": "2026-11-20",
    "warehouse_id": "W01",
    "destination_warehouse_id": "W02",
    "sku": "FF-GT250-S304-PN63-WE",
    "quantity": 42,
    "quantity_direction": "out",
    "order_id": null,
    "order_line_id": null,
    "production_batch_id": null,
    "reason_code": "replenishment",
    "reference_id": null
  },
  {
    "event_type": "inventory_movements",
    "event_id": "a6c973f1-28d9-4c43-9ad4-93d7b6fa084d",
    "movement_id": "MOV-4652",
    "movement_type": "transfer",
    "movement_date": "2026-11-20",
    "warehouse_id": "W02",
    "destination_warehouse_id": null,
    "sku": "FF-GT250-S304-PN63-WE",
    "quantity": 42,
    "quantity_direction": "in",
    "order_id": null,
    "order_line_id": null,
    "production_batch_id": null,
    "reason_code": "replenishment",
    "reference_id": "W01"
  },
  {
    "event_type": "inventory_movements",
    "event_id": "ec3c6c2f-4357-4a5b-8639-044ffa60bb32",
    "movement_id": "MOV-4653",
    "movement_type": "transfer",
    "movement_date": "2026-11-20",
    "warehouse_id": "W01",
    "destination_warehouse_id": "W02",
    "sku": "FF-GT100-S316-PN10-FM",
    "quantity": 27,
    "quantity_direction": "out",
    "order_id": null,
    "order_line_id": null,
    "production_batch_id": null,
    "reason_code": "replenishment",
    "reference_id": null
  },
  {
    "event_type": "inventory_movements",
    "event_id": "0872dd5f-dbc9-45af-900d-7e511198e0c2",
    "movement_id": "MOV-4654",
    "movement_type": "transfer",
    "movement_date": "2026-11-20",
    "warehouse_id": "W02",
    "destination_warehouse_id": null,
    "sku": "FF-GT100-S316-PN10-FM",
    "quantity": 27,
    "quantity_direction": "in",
    "order_id": null,
    "order_line_id": null,
    "production_batch_id": null,
    "reason_code": "replenishment",
    "reference_id": "W01"
  },
  {
    "event_type": "inventory_movements",
    "event_id": "d2d41295-d499-404b-a8c6-9654c70c8d0e",
    "movement_id": "MOV-4655",
    "movement_type": "transfer",
    "movement_date": "2026-11-20",
    "warehouse_id": "W01",
    "destination_warehouse_id": "W02",
    "sku": "FF-GT100-CS-PN10-WM",
    "quantity": 49,
    "quantity_direction": "out",
    "order_id": null,
    "order_line_id": null,
    "production_batch_id": null,
    "reason_code": "replenishment",
    "reference_id": null
  },
  {
    "event_type": "inventory_movements",
    "event_id": "830a1a2e-8c64-4fdf-9e43-6ed8ecfeaea5",
    "movement_id": "MOV-4656",
    "movement_type": "transfer",
    "movement_date": "2026-11-20",
    "warehouse_id": "W02",
    "destination_warehouse_id": null,
    "sku": "FF-GT100-CS-PN10-WM",
    "quantity": 49,
    "quantity_direction": "in",
    "order_id": null,
    "order_line_id": null,
    "production_batch_id": null,
    "reason_code": "replenishment",
    "reference_id": "W01"
  }
]