[
  {
    "event_type": "return_event",
    "event_id": "85e4f1ee-d21a-4ab7-a223-31ee5536c358",
    "event_subtype": "in_transit_return",
    "rma_id": "RMA-1148",
    "order_id": "ORD-2026-001129",
    "customer_id": "CUST-0031",
    "carrier_code": "BALTIC",
    "return_warehouse_id": "W01",
    "lines": [
      {
        "line_id": "ORD-2026-001129-L1",
        "sku": "FF-GL100-S304-PN10-FP",
        "quantity_returned": 7,
        "quantity_accepted": null,
        "return_reason": "damaged_in_transit"
      },
      {
        "line_id": "ORD-2026-001129-L2",
        "sku": "FF-GL100-S304-PN10-TM",
        "quantity_returned": 5,
        "quantity_accepted": null,
        "return_reason": "damaged_in_transit"
      }
    ],
    "resolution": null,
    "return_reason": "damaged_in_transit",
    "rma_status": "in_transit_return",
    "simulation_date": "2026-10-01",
    "timestamp": "2026-10-01T09:00:00Z",
    "sync_window": "08"
  },
  {
    "event_type": "return_event",
    "event_id": "78d47901-3b39-48ef-8e13-0b1823c9d2a9",
    "event_subtype": "in_transit_return",
    "rma_id": "RMA-1149",
    "order_id": "ORD-2026-001729",
    "customer_id": "CUST-0052",
    "carrier_code": "DBSC",
    "return_warehouse_id": "W01",
    "lines": [
      {
        "line_id": "ORD-2026-001729-L2",
        "sku": "FF-GT250-S304-PN16-FE",
        "quantity_returned": 44,
        "quantity_accepted": null,
        "return_reason": "damaged_in_transit"
      }
    ],
    "resolution": null,
    "return_reason": "damaged_in_transit",
    "rma_status": "in_transit_return",
    "simulation_date": "2026-10-01",
    "timestamp": "2026-10-01T09:00:00Z",
    "sync_window": "08"
  },
  {
    "event_type": "return_event",
    "event_id": "5d7aa4a8-b9bf-4b75-8416-f74761503c43",
    "event_subtype": "pickup_scheduled",
    "rma_id": "RMA-1150",
    "order_id": "ORD-2026-001378",
    "customer_id": "CUST-0022",
    "carrier_code": "DBSC",
    "return_warehouse_id": "W01",
    "lines": [
      {
        "line_id": "ORD-2026-001378-L2",
        "sku": "FF-BL250-S304-PN16-FH",
        "quantity_returned": 6,
        "quantity_accepted": null,
        "return_reason": "specification_mismatch"
      }
    ],
    "resolution": null,
    "return_reason": "specification_mismatch",
    "rma_status": "pickup_scheduled",
    "simulation_date": "2026-10-01",
    "timestamp": "2026-10-01T09:00:00Z",
    "sync_window": "08"
  },
  {
    "event_type": "return_event",
    "event_id": "1401d054-234b-44c9-8653-cae128a25b02",
    "event_subtype": "pickup_scheduled",
    "rma_id": "RMA-1151",
    "order_id": "ORD-2026-001695",
    "customer_id": "CUST-0052",
    "carrier_code": "DBSC",
    "return_warehouse_id": "W01",
    "lines": [
      {
        "line_id": "ORD-2026-001695-L1",
        "sku": "FF-GL80-S316-PN25-WP",
        "quantity_returned": 89,
        "quantity_accepted": null,
        "return_reason": "damaged_in_transit"
      }
    ],
    "resolution": null,
    "return_reason": "damaged_in_transit",
    "rma_status": "pickup_scheduled",
    "simulation_date": "2026-10-01",
    "timestamp": "2026-10-01T09:00:00Z",
    "sync_window": "08"
  },
  {
    "event_type": "return_event",
    "event_id": "48409c7b-360d-4f27-a1b6-d6b280b7b1ad",
    "event_subtype": "return_authorized",
    "rma_id": "RMA-1152",
    "order_id": "ORD-2026-001014",
    "customer_id": "CUST-0043",
    "carrier_code": "RABEN",
    "return_warehouse_id": "W01",
    "lines": [
      {
        "line_id": "ORD-2026-001014-L2",
        "sku": "FF-BF40-S304-PN40-TP",
        "quantity_returned": 12,
        "quantity_accepted": null,
        "return_reason": "quality_defect"
      }
    ],
    "resolution": null,
    "return_reason": "quality_defect",
    "rma_status": "return_authorized",
    "simulation_date": "2026-10-01",
    "timestamp": "2026-10-01T09:00:00Z",
    "sync_window": "08"
  },
  {
    "event_type": "return_event",
    "event_id": "13679729-d278-46c0-8696-fd5ffe8cf81a",
    "event_subtype": "return_authorized",
    "rma_id": "RMA-1153",
    "order_id": "ORD-2026-001074",
    "customer_id": "CUST-0053",
    "carrier_code": "DHL",
    "return_warehouse_id": "W01",
    "lines": [
      {
        "line_id": "ORD-2026-001074-L2",
        "sku": "FF-CK40-S316-PN10-FP",
        "quantity_returned": 20,
        "quantity_accepted": null,
        "return_reason": "overstock"
      },
      {
        "line_id": "ORD-2026-001074-L1",
        "sku": "FF-BF250-CS-PN10-FP",
        "quantity_returned": 18,
        "quantity_accepted": null,
        "return_reason": "overstock"
      }
    ],
    "resolution": null,
    "return_reason": "overstock",
    "rma_status": "return_authorized",
    "simulation_date": "2026-10-01",
    "timestamp": "2026-10-01T09:00:00Z",
    "sync_window": "08"
  },
  {
    "event_type": "return_event",
    "event_id": "2d85f085-1901-4b2a-8a9b-c0330d75ecc9",
    "event_subtype": "return_authorized",
    "rma_id": "RMA-1154",
    "order_id": "ORD-2026-001386",
    "customer_id": "CUST-0036",
    "carrier_code": "RABEN",
    "return_warehouse_id": "W01",
    "lines": [
      {
        "line_id": "ORD-2026-001386-L2",
        "sku": "FF-BF100-CS-PN25-XM",
        "quantity_returned": 5,
        "quantity_accepted": null,
        "return_reason": "quality_defect"
      },
      {
        "line_id": "ORD-2026-001386-L4",
        "sku": "FF-GL80-CS-PN25-FM",
        "quantity_returned": 6,
        "quantity_accepted": null,
        "return_reason": "quality_defect"
      },
      {
        "line_id": "ORD-2026-001386-L1",
        "sku": "FF-BF50-S304-PN25-FM",
        "quantity_returned": 4,
        "quantity_accepted": null,
        "return_reason": "quality_defect"
      },
      {
        "line_id": "ORD-2026-001386-L3",
        "sku": "FF-BL80-S304-PN25-TP",
        "quantity_returned": 5,
        "quantity_accepted": null,
        "return_reason": "quality_defect"
      }
    ],
    "resolution": null,
    "return_reason": "quality_defect",
    "rma_status": "return_authorized",
    "simulation_date": "2026-10-01",
    "timestamp": "2026-10-01T09:00:00Z",
    "sync_window": "08"
  },
  {
    "event_type": "return_event",
    "event_id": "8ac78e5b-44a1-4d36-9552-8128cbc9ed59",
    "event_subtype": "return_authorized",
    "rma_id": "RMA-1155",
    "order_id": "ORD-2026-001487",
    "customer_id": "CUST-0019",
    "carrier_code": "DHL",
    "return_warehouse_id": "W01",
    "lines": [
      {
        "line_id": "ORD-2026-001487-L2",
        "sku": "FF-BF150-CS-PN16-TM",
        "quantity_returned": 12,
        "quantity_accepted": null,
        "return_reason": "specification_mismatch"
      },
      {
        "line_id": "ORD-2026-001487-L3",
        "sku": "FF-BF50-BRS-PN10-XM",
        "quantity_returned": 14,
        "quantity_accepted": null,
        "return_reason": "specification_mismatch"
      }
    ],
    "resolution": null,
    "return_reason": "specification_mismatch",
    "rma_status": "return_authorized",
    "simulation_date": "2026-10-01",
    "timestamp": "2026-10-01T09:00:00Z",
    "sync_window": "08"
  }
]