[
  {
    "event_type": "inventory_movements",
    "event_id": "26574d28-58de-4a16-b81a-a8f28c81baf3",
    "movement_id": "MOV-4444",
    "movement_type": "receipt",
    "movement_date": "2026-11-02",
    "warehouse_id": "W01",
    "destination_warehouse_id": null,
    "sku": "FF-GL50-S304-PN40-FP",
    "quantity": 63,
    "quantity_direction": "in",
    "order_id": null,
    "order_line_id": null,
    "production_batch_id": "BATCH-2163",
    "reason_code": null,
    "reference_id": "GRADE-A"
  },
  {
    "event_type": "inventory_movements",
    "event_id": "efa40f4f-cbdb-4259-bcfa-bae9c871cd8e",
    "movement_id": "MOV-4445",
    "movement_type": "receipt",
    "movement_date": "2026-11-02",
    "warehouse_id": "W01",
    "destination_warehouse_id": null,
    "sku": "FF-GT80-S316-PN16-TM",
    "quantity": 82,
    "quantity_direction": "in",
    "order_id": null,
    "order_line_id": null,
    "production_batch_id": "BATCH-2164",
    "reason_code": null,
    "reference_id": "GRADE-A"
  },
  {
    "event_type": "inventory_movements",
    "event_id": "75931eb6-0c6c-4fe4-a1ab-772b0ee39ea5",
    "movement_id": "MOV-4446",
    "movement_type": "receipt",
    "movement_date": "2026-11-02",
    "warehouse_id": "W01",
    "destination_warehouse_id": null,
    "sku": "FF-GL150-S316-PN10-TM",
    "quantity": 56,
    "quantity_direction": "in",
    "order_id": null,
    "order_line_id": null,
    "production_batch_id": "BATCH-2165",
    "reason_code": null,
    "reference_id": "GRADE-A"
  },
  {
    "event_type": "inventory_movements",
    "event_id": "f03321f8-0d24-49e9-9b73-81bb344540aa",
    "movement_id": "MOV-4447",
    "movement_type": "receipt",
    "movement_date": "2026-11-02",
    "warehouse_id": "W01",
    "destination_warehouse_id": null,
    "sku": "FF-GL100-DPX-PN16-FP",
    "quantity": 33,
    "quantity_direction": "in",
    "order_id": null,
    "order_line_id": null,
    "production_batch_id": "BATCH-2166",
    "reason_code": null,
    "reference_id": "GRADE-A"
  },
  {
    "event_type": "inventory_movements",
    "event_id": "22254f2c-09b5-415b-b403-9d96deabc5d9",
    "movement_id": "MOV-4448",
    "movement_type": "receipt",
    "movement_date": "2026-11-02",
    "warehouse_id": "W01",
    "destination_warehouse_id": null,
    "sku": "FF-GL50-S316-PN16-FP",
    "quantity": 80,
    "quantity_direction": "in",
    "order_id": null,
    "order_line_id": null,
    "production_batch_id": "BATCH-2167",
    "reason_code": null,
    "reference_id": "GRADE-A"
  },
  {
    "event_type": "inventory_movements",
    "event_id": "b2d76ca6-aadf-41dd-b7d0-938dd0c45b65",
    "movement_id": "MOV-4449",
    "movement_type": "receipt",
    "movement_date": "2026-11-02",
    "warehouse_id": "W01",
    "destination_warehouse_id": null,
    "sku": "FF-BL100-S316-PN25-WP",
    "quantity": 38,
    "quantity_direction": "in",
    "order_id": null,
    "order_line_id": null,
    "production_batch_id": "BATCH-2168",
    "reason_code": null,
    "reference_id": "GRADE-A"
  },
  {
    "event_type": "inventory_movements",
    "event_id": "b702305d-c311-4917-ad1d-a803914dfa9a",
    "movement_id": "MOV-4450",
    "movement_type": "receipt",
    "movement_date": "2026-11-02",
    "warehouse_id": "W01",
    "destination_warehouse_id": null,
    "sku": "FF-GT50-S304-PN63-FM",
    "quantity": 76,
    "quantity_direction": "in",
    "order_id": null,
    "order_line_id": null,
    "production_batch_id": "BATCH-2169",
    "reason_code": null,
    "reference_id": "GRADE-A"
  },
  {
    "event_type": "inventory_movements",
    "event_id": "5dbdffb3-9580-42f3-bf75-cd567144d88c",
    "movement_id": "MOV-4451",
    "movement_type": "receipt",
    "movement_date": "2026-11-02",
    "warehouse_id": "W01",
    "destination_warehouse_id": null,
    "sku": "FF-BF100-S316-PN16-FP",
    "quantity": 38,
    "quantity_direction": "in",
    "order_id": null,
    "order_line_id": null,
    "production_batch_id": "BATCH-2170",
    "reason_code": null,
    "reference_id": "GRADE-A"
  },
  {
    "event_type": "inventory_movements",
    "event_id": "3119d3f2-1f2e-49b2-9877-380f534ddd60",
    "movement_id": "MOV-4452",
    "movement_type": "return_restock",
    "movement_date": "2026-11-02",
    "warehouse_id": "W01",
    "destination_warehouse_id": null,
    "sku": "FF-BF150-S316-PN10-XM",
    "quantity": 18,
    "quantity_direction": "in",
    "order_id": "ORD-2026-001117",
    "order_line_id": null,
    "production_batch_id": null,
    "reason_code": null,
    "reference_id": "GRADE-A"
  }
]