[
  {
    "event_type": "customer_order",
    "event_id": "71d44be0-7b82-48ca-848e-da2fe3ef408f",
    "order_id": "ORD-2026-002350",
    "customer_id": "CUST-0015",
    "simulation_date": "2026-08-25",
    "timestamp": "2026-08-25T11:23:01",
    "currency": "PLN",
    "priority": "express",
    "status": "confirmed",
    "requested_delivery_date": "2026-09-01",
    "lines": [
      {
        "line_id": "ORD-2026-002350-L1",
        "sku": "FF-BL150-S316-PN63-WM",
        "quantity_ordered": 4,
        "quantity_allocated": 0,
        "quantity_shipped": 0,
        "quantity_backordered": 0,
        "unit_price": 11899.23,
        "line_status": "open"
      },
      {
        "line_id": "ORD-2026-002350-L2",
        "sku": "FF-ND40-S316-PN16-FM",
        "quantity_ordered": 3,
        "quantity_allocated": 0,
        "quantity_shipped": 0,
        "quantity_backordered": 0,
        "unit_price": 1041.68,
        "line_status": "open"
      }
    ],
    "sales_channel": "portal",
    "incoterms": "FCA"
  },
  {
    "event_type": "customer_order",
    "event_id": "68f017f2-0efb-4668-a7a6-0eeb41aa084e",
    "order_id": "ORD-2026-002351",
    "customer_id": "CUST-0026",
    "simulation_date": "2026-08-25",
    "timestamp": "2026-08-25T09:38:26",
    "currency": "PLN",
    "priority": "standard",
    "status": "confirmed",
    "requested_delivery_date": "2026-09-09",
    "lines": [
      {
        "line_id": "ORD-2026-002351-L1",
        "sku": "FF-BL150-CS-PN25-FH",
        "quantity_ordered": 56,
        "quantity_allocated": 0,
        "quantity_shipped": 0,
        "quantity_backordered": 0,
        "unit_price": 10291.52,
        "line_status": "open"
      },
      {
        "line_id": "ORD-2026-002351-L2",
        "sku": "FF-GT200-S316-PN16-WE",
        "quantity_ordered": 70,
        "quantity_allocated": 0,
        "quantity_shipped": 0,
        "quantity_backordered": 0,
        "unit_price": 25500.82,
        "line_status": "open"
      },
      {
        "line_id": "ORD-2026-002351-L3",
        "sku": "FF-BL100-DPX-PN40-TP",
        "quantity_ordered": 71,
        "quantity_allocated": 0,
        "quantity_shipped": 0,
        "quantity_backordered": 0,
        "unit_price": 8631.84,
        "line_status": "open"
      }
    ],
    "sales_channel": "direct",
    "incoterms": "DDP"
  },
  {
    "event_type": "customer_order",
    "event_id": "bcb0f29a-bf8f-48de-8d02-eec38487c900",
    "order_id": "ORD-2026-002352",
    "customer_id": "CUST-0038",
    "simulation_date": "2026-08-25",
    "timestamp": "2026-08-25T10:14:33",
    "currency": "PLN",
    "priority": "standard",
    "status": "confirmed",
    "requested_delivery_date": "2026-09-23",
    "lines": [
      {
        "line_id": "ORD-2026-002352-L1",
        "sku": "FF-BL80-S316-PN25-FE",
        "quantity_ordered": 65,
        "quantity_allocated": 0,
        "quantity_shipped": 0,
        "quantity_backordered": 0,
        "unit_price": 4906.89,
        "line_status": "open"
      },
      {
        "line_id": "ORD-2026-002352-L2",
        "sku": "FF-BF150-S316-PN16-XP",
        "quantity_ordered": 53,
        "quantity_allocated": 0,
        "quantity_shipped": 0,
        "quantity_backordered": 0,
        "unit_price": 6141.24,
        "line_status": "open"
      }
    ],
    "sales_channel": "direct",
    "incoterms": "DDP"
  },
  {
    "event_type": "customer_order",
    "event_id": "0a729c2f-cfc9-4032-8bd8-144ba3d9dbf7",
    "order_id": "ORD-2026-002353",
    "customer_id": "CUST-0043",
    "simulation_date": "2026-08-25",
    "timestamp": "2026-08-25T11:55:44",
    "currency": "EUR",
    "priority": "standard",
    "status": "confirmed",
    "requested_delivery_date": "2026-09-16",
    "lines": [
      {
        "line_id": "ORD-2026-002353-L1",
        "sku": "FF-GT150-CS-PN25-FP",
        "quantity_ordered": 17,
        "quantity_allocated": 0,
        "quantity_shipped": 0,
        "quantity_backordered": 0,
        "unit_price": 1794.27,
        "line_status": "open"
      }
    ],
    "sales_channel": "portal",
    "incoterms": "DDP"
  },
  {
    "event_type": "customer_order",
    "event_id": "38460d7d-63dd-45b2-849c-eba77dcf96ed",
    "order_id": "ORD-2026-002354",
    "customer_id": "CUST-0045",
    "simulation_date": "2026-08-25",
    "timestamp": "2026-08-25T10:56:05",
    "currency": "PLN",
    "priority": "standard",
    "status": "confirmed",
    "requested_delivery_date": "2026-09-21",
    "lines": [
      {
        "line_id": "ORD-2026-002354-L1",
        "sku": "FF-BF150-S316-PN16-WE",
        "quantity_ordered": 117,
        "quantity_allocated": 0,
        "quantity_shipped": 0,
        "quantity_backordered": 0,
        "unit_price": 8693.62,
        "line_status": "open"
      },
      {
        "line_id": "ORD-2026-002354-L2",
        "sku": "FF-BL150-S316-PN25-WH",
        "quantity_ordered": 95,
        "quantity_allocated": 0,
        "quantity_shipped": 0,
        "quantity_backordered": 0,
        "unit_price": 17944.53,
        "line_status": "open"
      },
      {
        "line_id": "ORD-2026-002354-L3",
        "sku": "FF-BF300-S316-PN63-WM",
        "quantity_ordered": 81,
        "quantity_allocated": 0,
        "quantity_shipped": 0,
        "quantity_backordered": 0,
        "unit_price": 38960.3,
        "line_status": "open"
      },
      {
        "line_id": "ORD-2026-002354-L4",
        "sku": "FF-BF100-CS-PN63-FP",
        "quantity_ordered": 104,
        "quantity_allocated": 0,
        "quantity_shipped": 0,
        "quantity_backordered": 0,
        "unit_price": 3229.33,
        "line_status": "open"
      },
      {
        "line_id": "ORD-2026-002354-L5",
        "sku": "FF-BL200-DPX-PN25-TP",
        "quantity_ordered": 56,
        "quantity_allocated": 0,
        "quantity_shipped": 0,
        "quantity_backordered": 0,
        "unit_price": 24931.33,
        "line_status": "open"
      }
    ],
    "sales_channel": "edi",
    "incoterms": "DAP"
  },
  {
    "event_type": "customer_order",
    "event_id": "ab947d6d-8cc1-4ce7-9bb9-b446be7e3b90",
    "order_id": "ORD-2026-002355",
    "customer_id": "CUST-0057",
    "simulation_date": "2026-08-25",
    "timestamp": "2026-08-25T14:32:22",
    "currency": "EUR",
    "priority": "standard",
    "status": "confirmed",
    "requested_delivery_date": "2026-09-11",
    "lines": [
      {
        "line_id": "ORD-2026-002355-L1",
        "sku": "FF-GL150-S304-PN40-WE",
        "quantity_ordered": 42,
        "quantity_allocated": 0,
        "quantity_shipped": 0,
        "quantity_backordered": 0,
        "unit_price": 4847.2,
        "line_status": "open"
      },
      {
        "line_id": "ORD-2026-002355-L2",
        "sku": "FF-BF100-S316-PN40-FM",
        "quantity_ordered": 49,
        "quantity_allocated": 0,
        "quantity_shipped": 0,
        "quantity_backordered": 0,
        "unit_price": 760.06,
        "line_status": "open"
      },
      {
        "line_id": "ORD-2026-002355-L3",
        "sku": "FF-BL250-CS-PN25-TE",
        "quantity_ordered": 47,
        "quantity_allocated": 0,
        "quantity_shipped": 0,
        "quantity_backordered": 0,
        "unit_price": 6040.48,
        "line_status": "open"
      }
    ],
    "sales_channel": "edi",
    "incoterms": "DAP"
  }
]