[
  {
    "event_type": "backorder",
    "event_id": "eeda6f73-bd85-4545-aa12-8eb089e914ea",
    "backorder_date": "2026-06-03",
    "order_id": "ORD-2026-001261",
    "order_line_id": "ORD-2026-001261-L3",
    "sku": "FF-CK40-S316-PN16-FM",
    "quantity_backordered": 14,
    "quantity_allocated": 0,
    "backorder_reason": "no_stock",
    "days_backordered": 2,
    "escalated_to_express": false
  },
  {
    "event_type": "backorder",
    "event_id": "adfd8061-acfc-45d0-8d59-c120d2604e4c",
    "backorder_date": "2026-06-03",
    "order_id": "ORD-2026-001338",
    "order_line_id": "ORD-2026-001338-L1",
    "sku": "FF-GL40-CS-PN16-FM",
    "quantity_backordered": 695784701952,
    "quantity_allocated": 0,
    "backorder_reason": "no_stock",
    "days_backordered": 34,
    "escalated_to_express": false
  },
  {
    "event_type": "backorder",
    "event_id": "f17d8b12-6b14-4126-87af-83cf44af741a",
    "backorder_date": "2026-06-03",
    "order_id": "ORD-2026-001032",
    "order_line_id": "ORD-2026-001032-L1",
    "sku": "FF-BF50-CS-PN10-WE",
    "quantity_backordered": 4096,
    "quantity_allocated": 0,
    "backorder_reason": "no_stock",
    "days_backordered": 9,
    "escalated_to_express": false
  }
]